{
  "name": "dowdiness/crdt",
  "version": "0.1.0",
  "deps": {
    "moonbitlang/quickcheck": "0.9.9",
    "dowdiness/event-graph-walker": {
      "path": "./event-graph-walker"
    },
    "dowdiness/text_change": {
      "path": "./lib/text-change"
    },
    "dowdiness/incr": {
      "path": "./loom/incr"
    },
    "dowdiness/lambda": {
      "path": "./loom/examples/lambda"
    },
    "dowdiness/loom": {
      "path": "./loom/loom"
    },
    "dowdiness/seam": {
      "path": "./loom/seam"
    }
  },
  "readme": "README.mbt.md",
  "repository": "https://github.com/dowdiness/crdt",
  "license": "Apache-2.0",
  "keywords": ["crdt", "collaborative-editing", "lambda-calculus"],
  "description": "Lambda Calculus CRDT Editor - eg-walker implementation in MoonBit",
  "preferred-target": "js"
}
